CHANGELOG.md
LICENSE
MANIFEST.in
README.md
requirements.txt
setup.py
docs/Makefile
docs/api.rst
docs/changelog.rst
docs/conf.py
docs/index.rst
docs/installation.rst
docs/license.rst
docs/limitations.rst
docs/make.bat
docs/recipes.rst
docs/usage.rst
python_react_v8.egg-info/PKG-INFO
python_react_v8.egg-info/SOURCES.txt
python_react_v8.egg-info/dependency_links.txt
python_react_v8.egg-info/not-zip-safe
python_react_v8.egg-info/requires.txt
python_react_v8.egg-info/top_level.txt
react/__init__.py
react/excepts.py
react/react.py
react/utils.py
tests/__init__.py
tests/tests_react.py
tests/tests_utils.py