Metadata-Version: 1.1
Name: python-react-v8
Version: 0.1.1
Summary: Thin wrapper around v8-cffi to render React views server-side.
Home-page: https://github.com/nitely/python-react-v8
Author: Esteban Castro Borsani
Author-email: ecastroborsani@gmail.com
License: MIT License
Platform: UNKNOWN
Classifier: Development Status :: 5 - Production/Stable
Classifier: Environment :: Web Environment
Classifier: Intended Audience :: Developers
Classifier: License :: OSI Approved :: MIT License
Classifier: Operating System :: OS Independent
Classifier: Programming Language :: Python
Classifier: Programming Language :: Python :: 3
Classifier: Topic :: Internet :: WWW/HTTP
Classifier: Topic :: Internet :: WWW/HTTP :: Dynamic Content
